atris/__init__.py
atris/anomaly_models.py
atris/classification_models.py
atris/ensemble.py
atris/eval.py
atris/features.py
atris/models.py
atris/process.py
atris/regression_models.py
atris-0.1.0.dist-info/licenses/LICENSE
atris-0.1.0.dist-info/METADATA
atris-0.1.0.dist-info/WHEEL
atris-0.1.0.dist-info/top_level.txt
atris-0.1.0.dist-info/RECORD
